fasttext_pybind.cpython-39-x86_64-linux-gnu.so
fasttext/FastText.py
fasttext/__init__.py
fasttext/pybind/fasttext_pybind.cc
fasttext/tests/__init__.py
fasttext/tests/helpers.py
fasttext/tests/test_configurations.py
fasttext/tests/test_script.py
fasttext/util/__init__.py
fasttext/util/util.py
fasttext_community-0.10.8.dist-info/METADATA
fasttext_community-0.10.8.dist-info/WHEEL
fasttext_community-0.10.8.dist-info/top_level.txt
fasttext_community-0.10.8.dist-info/RECORD
fasttext_community-0.10.8.dist-info/licenses/LICENSE
