Metadata-Version: 2.4
Name: fasttext-community
Version: 0.10.8
Summary: fasttext Python bindings
Author-email: Nurzhan Muratkhan <nurzhanmuratkhan@gmail.com>
License-Expression: MIT
Project-URL: Homepage, https://github.com/munlicode/fasttext-community
Classifier: Development Status :: 3 - Alpha
Classifier: Intended Audience :: Developers
Classifier: Intended Audience :: Science/Research
Classifier: Topic :: Software Development
Classifier: Topic :: Scientific/Engineering
Requires-Python: >=3.9
License-File: LICENSE
Requires-Dist: pybind11>=2.2
Requires-Dist: setuptools>=0.7.0
Requires-Dist: numpy
Provides-Extra: test
Requires-Dist: pytest; extra == "test"
Provides-Extra: dev
Requires-Dist: pytest; extra == "dev"
Requires-Dist: build; extra == "dev"
Requires-Dist: twine; extra == "dev"
Dynamic: license-file
